{
  "main": {
    "id": "7b3efc5b3673307f",
    "type": "split",
    "children": [
      {
        "id": "208818918cf12d48",
        "type": "tabs",
        "children": [
          {
            "id": "85b7640dc3c9e286",
            "type": "leaf",
            "state": {
              "type": "markdown",
              "state": {
                "file": "Java/JavaWeb/Tomcat.md",
                "mode": "source",
                "backlinks": true,
                "source": false
              }
            }
          },
          {
            "id": "fe3126fcf48fa44b",
            "type": "leaf",
            "state": {
              "type": "markdown",
              "state": {
                "file": "Java/JavaWeb/Servler.md",
                "mode": "source",
                "backlinks": true,
                "source": false
              }
            }
          }
        ],
        "currentTab": 1
      }
    ],
    "direction": "vertical"
  },
  "left": {
    "id": "e9161eb2593d670f",
    "type": "split",
    "children": [
      {
        "id": "e109eac1f5bfa8cc",
        "type": "tabs",
        "children": [
          {
            "id": "718b461576e7a505",
            "type": "leaf",
            "state": {
              "type": "file-explorer",
              "state": {
                "sortOrder": "byCreatedTime"
              }
            }
          },
          {
            "id": "e780c53324acad0e",
            "type": "leaf",
            "state": {
              "type": "search",
              "state": {
                "query": "",
                "matchingCase": true,
                "explainSearch": false,
                "collapseAll": true,
                "extraContext": false,
                "sortOrder": "alphabetical"
              }
            }
          },
          {
            "id": "03368f4884cd1528",
            "type": "leaf",
            "state": {
              "type": "recent-files",
              "state": {}
            }
          }
        ]
      }
    ],
    "direction": "horizontal",
    "width": 204,
    "collapsed": true
  },
  "right": {
    "id": "1d0dfb31d3197d39",
    "type": "split",
    "children": [
      {
        "id": "e872ed86d871d364",
        "type": "tabs",
        "children": [
          {
            "id": "c3c39f74f52c2fb0",
            "type": "leaf",
            "state": {
              "type": "outline",
              "state": {
                "file": "Java/JavaWeb/Servler.md"
              }
            }
          },
          {
            "id": "a0504de5eb1c5901",
            "type": "leaf",
            "state": {
              "type": "outgoing-link",
              "state": {
                "file": "Java/JavaWeb/Servler.md",
                "linksCollapsed": false,
                "unlinkedCollapsed": true
              }
            }
          },
          {
            "id": "3cc7a0a29a1479b9",
            "type": "leaf",
            "state": {
              "type": "tag",
              "state": {
                "sortOrder": "frequency",
                "useHierarchy": true
              }
            }
          },
          {
            "id": "6bfc4d3d64b7dd3f",
            "type": "leaf",
            "state": {
              "type": "backlink",
              "state": {
                "file": "Java/JavaWeb/Servler.md",
                "collapseAll": false,
                "extraContext": false,
                "sortOrder": "alphabetical",
                "showSearch": false,
                "searchQuery": "",
                "backlinkCollapsed": false,
                "unlinkedCollapsed": true
              }
            }
          }
        ]
      }
    ],
    "direction": "horizontal",
    "width": 233,
    "collapsed": true
  },
  "active": "c3c39f74f52c2fb0",
  "lastOpenFiles": [
    "Java/JavaWeb/Tomcat.md",
    "Java/JavaWeb/Servler.md",
    "Javascript/WebAPI.md",
    "算法/剑指offer/数组类.md",
    "Java/JavaSE/初识Java.md",
    "Java/JavaSE/数据类型与变量.md",
    "Java/未命名.md",
    "Javascript/js基础语法.md",
    "MySql/C语言连接数据库.md",
    "MySql/事务.md"
  ]
}